kpandiyaraj/__init__.py
kpandiyaraj/__main__.py
kpandiyaraj/qr.py
kpandiyaraj-1.0.0.dist-info/licenses/LICENSE
kpandiyaraj-1.0.0.dist-info/METADATA
kpandiyaraj-1.0.0.dist-info/WHEEL
kpandiyaraj-1.0.0.dist-info/entry_points.txt
kpandiyaraj-1.0.0.dist-info/top_level.txt
kpandiyaraj-1.0.0.dist-info/RECORD
