Metadata-Version: 2.4
Name: kpandiyaraj
Version: 1.0.0
Summary: Display QR code for K Pandiyaraj's LinkedIn profile in your terminal
Author-email: Pandiyaraj K <hello@example.com>
License: MIT
Project-URL: Homepage, https://www.linkedin.com/in/pandiyaraj-k-49353467/
Project-URL: Repository, https://github.com/pandiyaraj
Keywords: qr,qrcode,linkedin,profile,terminal,cli
Classifier: Development Status :: 5 - Production/Stable
Classifier: Intended Audience :: Developers
Classifier: Intended Audience :: End Users/Desktop
Classifier: License :: OSI Approved :: MIT License
Classifier: Programming Language :: Python :: 3
Classifier: Programming Language :: Python :: 3.8
Classifier: Programming Language :: Python :: 3.9
Classifier: Programming Language :: Python :: 3.10
Classifier: Programming Language :: Python :: 3.11
Classifier: Programming Language :: Python :: 3.12
Classifier: Topic :: Terminals
Requires-Python: >=3.8
License-File: LICENSE
Requires-Dist: qrcode[pil]>=7.4.2
Dynamic: license-file
